onstrodb/__init__.py
onstrodb/cli/__init__.py
onstrodb/cli/common.py
onstrodb/cli/main.py
onstrodb/cli/utils.py
onstrodb/core/__init__.py
onstrodb/core/db.py
onstrodb/core/utils.py
onstrodb/errors/__init__.py
onstrodb/errors/common_errors.py
onstrodb/errors/schema_errors.py
onstro_db-0.2.2.dist-info/LICENSE
onstro_db-0.2.2.dist-info/METADATA
onstro_db-0.2.2.dist-info/WHEEL
onstro_db-0.2.2.dist-info/entry_points.txt
onstro_db-0.2.2.dist-info/top_level.txt
onstro_db-0.2.2.dist-info/RECORD
