Metadata-Version: 2.1
Name: onstro-db
Version: 0.2.2
Summary: A simple and efficient DataBase designed to store and use large amounts of data.
Home-page: https://github.com/Adwaith-Rajesh/onstro-db
Author: Adwaith Rajesh
Author-email: adwaithrajesh3180@gmail.com
License: MIT
Platform: UNKNOWN
Classifier: License :: OSI Approved :: MIT License
Classifier: Programming Language :: Python :: 3
Classifier: Programming Language :: Python :: 3 :: Only
Classifier: Programming Language :: Python :: 3.7
Classifier: Programming Language :: Python :: 3.8
Requires-Python: >=3.8.0
Requires-Dist: pandas (>=1.3.0)
